LICENSE.txt
README.md
pyproject.toml
setup.cfg
setup.py
bin/gridless
bin/spotless
bin/spotless_calibrate
spotless/__init__.py
spotless/model.py
spotless/multi_spotless.py
spotless/source.py
spotless/sphere.py
spotless/spotless.py
spotless.egg-info/PKG-INFO
spotless.egg-info/SOURCES.txt
spotless.egg-info/dependency_links.txt
spotless.egg-info/requires.txt
spotless.egg-info/top_level.txt