Metadata-Version: 2.1
Name: spotless
Version: 0.4.0
Summary: Grid-Free Deconvolution Directly From Visibilities
Home-page: http://github.com/tmolteno/TART
Author: Tim Molteno
Author-email: tim@elec.ac.nz
License: GPLv3
Classifier: Development Status :: 4 - Beta
Classifier: Topic :: Scientific/Engineering
Classifier: Topic :: Communications :: Ham Radio
Classifier: License :: OSI Approved :: GNU General Public License v3 (GPLv3)
Classifier: Programming Language :: Python :: 3
Classifier: Programming Language :: Python :: 3.7
Classifier: Programming Language :: Python :: 3.8
Classifier: Programming Language :: Python :: 3.9
Classifier: Programming Language :: Python :: 3.10
Classifier: Programming Language :: Python :: 3 :: Only
Classifier: Intended Audience :: Science/Research
License-File: LICENSE.txt
